shape_fitting/__init__.py
shape_fitting-0.0.1.dist-info/METADATA
shape_fitting-0.0.1.dist-info/WHEEL
shape_fitting-0.0.1.dist-info/top_level.txt
shape_fitting-0.0.1.dist-info/RECORD
